{
    "adapter": "ac adapter",
    "adapter cable": "usb cord",
    "adapter cord": "usb cord",
    "adaptor": "ac adapter",
    "badge": "security badge",
    "big bucket": "large bucket",
    "cable": "usb cord",
    "cam": "camera",
    "cctv": "camera",
    "charge cable": "usb cord",
    "charge cord": "usb cord",
    "charging cable": "usb cord",
    "charging cord": "usb cord",
    "cord": "usb cord",
    "drive": "ssd",
    "elevator": "elevator key",
    "employee badge": "security badge",
    "engineer badge": "security badge",
    "external": "usb drive",
    "external drive": "usb drive",
    "external hard drive": "usb drive",
    "flash drive": "usb drive",
    "flashdrive": "usb drive",
    "hard disk": "ssd",
    "hard drive": "ssd",
    "hmi 25": "hmi-25",
    "hmi 50": "hmi-50",
    "hmi25": "hmi-25",
    "hmi50": "hmi-50",
    "key": "elevator key",
    "keycard": "security badge",
    "large backpack": "large bucket",
    "large pail": "large bucket",
    "lever": "lever",
    "panel": "button",
    "pin": "security badge",
    "pin badge": "security badge",
    "power adapter": "ac adapter",
    "power cable": "usb cord",
    "power cord": "usb cord",
    "small backpack": "small bucket",
    "small pail": "small bucket",
    "solid state": "ssd",
    "solid state disk": "ssd",
    "solid state drive": "ssd",
    "ss disk": "ssd",
    "ss drive": "ssd",
    "surveillance camera": "camera",
    "switch": "button",
    "thumb drive": "usb drive",
    "thumbdrive": "usb drive",
    "tiny bucket": "small bucket",
    "tool": "screwdriver",
    "usb": "usb drive",
    "usb cable": "usb cord",
    "video camera": "camera",
    "videocam": "camera",
    "wall button": "button",
    "wall panel": "button",
    "wall switch": "button"
}